healing_agent/__init__.py
healing_agent/ai_broker.py
healing_agent/ai_code_fixer.py
healing_agent/ai_hint_generator.py
healing_agent/code_backup.py
healing_agent/code_replacer.py
healing_agent/config_loader.py
healing_agent/configurator.py
healing_agent/exception_handler.py
healing_agent/exception_saver.py
healing_agent/healing_agent.py
healing_agent/healing_agent_config.py
healing_agent/agent_tools/tool_check_env_variables.py
healing_agent/agent_tools/tool_json_fixer.py
healing_agent/agent_tools/tool_list_files_functions.py
healing_agent-0.2.4.dist-info/METADATA
healing_agent-0.2.4.dist-info/WHEEL
healing_agent-0.2.4.dist-info/licenses/LICENSE
healing_agent-0.2.4.dist-info/RECORD
