Metadata-Version: 2.3
Name: healing_agent
Version: 0.2.4
Summary: An AI-powered agent that helps fix and heal buggy code
Project-URL: Homepage, https://github.com/matebenyovszky/healing-agent
Project-URL: Bug Tracker, https://github.com/matebenyovszky/healing-agent/issues
Project-URL: Documentation, https://github.com/matebenyovszky/healing-agent#readme
Project-URL: Repository, https://github.com/matebenyovszky/healing-agent.git
Project-URL: Changelog, https://github.com/matebenyovszky/healing-agent/blob/main/CHANGELOG.md
Author-email: Máté Benyovszky <benyovszky.mate.work@outlook.com>
License: MIT
License-File: LICENSE
Keywords: agent,ai,automation,bug-fixing,code-healing,code-repair,debugging,developer-tools,error-handling,exception-handling,openai
Classifier: Development Status :: 3 - Alpha
Classifier: Intended Audience :: Developers
Classifier: Intended Audience :: Information Technology
Classifier: License :: OSI Approved :: MIT License
Classifier: Natural Language :: English
Classifier: Operating System :: OS Independent
Classifier: Programming Language :: Python :: 3
Classifier: Programming Language :: Python :: 3.9
Classifier: Programming Language :: Python :: 3.10
Classifier: Programming Language :: Python :: 3.11
Classifier: Programming Language :: Python :: 3.12
Classifier: Topic :: Software Development :: Debuggers
Classifier: Topic :: Software Development :: Libraries :: Python Modules
Classifier: Topic :: Software Development :: Quality Assurance
Requires-Python: >=3.9
Requires-Dist: astor
Requires-Dist: openai>=1.12.0
Requires-Dist: requests>=2.28.2
